{"frameRate":60,"name":"xhy_zhujiemian","version":"5.5","compatibleVersion":"5.5","armature":[{"type":"Armature","frameRate":60,"name":"armatureName","aabb":{"x":-863.2,"y":-53,"width":1394,"height":609.45},"bone":[{"name":"root"},{"inheritScale":false,"name":"oo_25","parent":"root","transform":{"x":-539.55,"y":349.05,"skX":-9.8169,"scX":0.4199,"scY":0.4199}},{"inheritScale":false,"name":"dc_02","parent":"root","transform":{"x":-788.65,"y":412.65,"scX":3.98,"scY":3.98}},{"inheritScale":false,"name":"dc_03","parent":"root","transform":{"x":-645.25,"y":453.05,"scX":3.98,"scY":3.98}},{"inheritScale":false,"name":"oo_04","parent":"root","transform":{"x":-739.05,"y":452.2,"scX":0.8,"scY":0.8}},{"inheritScale":false,"name":"oo_05","parent":"root","transform":{"x":-550.35,"y":470.9,"scX":1.3,"scY":1.3}},{"inheritScale":false,"name":"dc_06","parent":"root","transform":{"x":240.4,"y":381.8,"scX":3.98,"scY":3.98}},{"inheritScale":false,"name":"oo_07","parent":"root","transform":{"x":172.95,"y":428.2,"scX":0.8,"scY":0.8}},{"inheritScale":false,"name":"oo_08","parent":"root","transform":{"x":368.15,"y":434.6,"scX":1.352,"scY":1.352}},{"inheritScale":false,"name":"oo_09","parent":"root","transform":{"x":-179.05,"y":385.05,"scX":1.352,"scY":1.352}},{"inheritScale":false,"name":"dc_10","parent":"root","transform":{"x":-299.7,"y":435.4,"scX":3.98,"scY":3.98}},{"inheritScale":false,"name":"dc_11","parent":"root","transform":{"x":-455.95,"y":489.5,"scX":3.98,"scY":3.98}},{"inheritScale":false,"name":"oo_12","parent":"root","transform":{"x":-835.7,"y":385.25,"skX":15.0015}},{"inheritScale":false,"name":"oo_13","parent":"root"},{"inheritScale":false,"name":"oo_14","parent":"root","transform":{"x":-750.45,"y":296.9,"skX":15.0032,"scX":0.5802,"scY":0.5802}},{"inheritScale":false,"name":"oo_15","parent":"root","transform":{"x":-726.1,"y":277.35,"skX":15.0016,"scX":0.4881,"scY":0.4881}},{"inheritScale":false,"name":"oo_16","parent":"root","transform":{"x":-712.2,"y":362.55,"skX":7.9963,"scX":0.584,"scY":0.584}},{"inheritScale":false,"name":"oo_17","parent":"root","transform":{"x":-758.75,"y":367.45,"skX":14.9971,"scX":0.384,"scY":0.384}},{"inheritScale":false,"name":"oo_18","parent":"root","transform":{"x":-784.25,"y":310.5,"skX":24.9967,"scX":0.4608,"scY":0.4608}},{"inheritScale":false,"name":"oo_19","parent":"root","transform":{"x":-533.9,"y":357.1}},{"inheritScale":false,"name":"oo_20","parent":"root","transform":{"x":-622.5,"y":309.35,"skX":9.8172,"scX":0.9994,"scY":0.9994}},{"inheritScale":false,"name":"oo_21","parent":"root","transform":{"x":-577.45,"y":380.75,"scX":0.64,"scY":0.64}},{"inheritScale":false,"name":"oo_22","parent":"root","transform":{"x":-595.5,"y":362.75,"scX":0.512,"scY":0.512}},{"inheritScale":false,"name":"oo_23","parent":"root","transform":{"x":-625.1,"y":447.5,"skX":6.8148,"scX":0.5998,"scY":0.5998}},{"inheritScale":false,"name":"oo_24","parent":"root","transform":{"x":-585.9,"y":446.45,"scX":0.384,"scY":0.384}},{"inheritScale":false,"name":"dc_01","parent":"root","transform":{"x":-421.2,"y":395.4,"scX":3.98,"scY":3.98}},{"inheritScale":false,"name":"oo_26","parent":"root","transform":{"x":140.05,"y":453.55}},{"inheritScale":false,"name":"oo_27","parent":"root","transform":{"x":240.2,"y":411.75,"skX":-9.8181,"scX":0.9994,"scY":0.9994}},{"inheritScale":false,"name":"oo_28","parent":"root","transform":{"x":194.15,"y":480.1,"scX":0.64,"scY":0.64}},{"inheritScale":false,"name":"oo_29","parent":"root"},{"inheritScale":false,"name":"oo_30","parent":"root"},{"inheritScale":false,"name":"oo_31","parent":"root","transform":{"x":207.6,"y":481.45,"scX":0.3615,"scY":0.3615}},{"inheritScale":false,"name":"oo_32","parent":"root","transform":{"x":156.9,"y":430.45,"skX":10.0044,"scX":0.4471,"scY":0.4471}},{"inheritScale":false,"name":"oo_33","parent":"root","transform":{"x":503.3,"y":426.5,"skX":-16.9811}},{"inheritScale":false,"name":"oo_34","parent":"root"},{"inheritScale":false,"name":"oo_35","parent":"root","transform":{"x":414.95,"y":341.05,"skX":-16.9844,"scX":0.5802,"scY":0.5802}},{"inheritScale":false,"name":"oo_36","parent":"root","transform":{"x":390.05,"y":322.25,"skX":-16.9847,"scX":0.4881,"scY":0.4881}},{"inheritScale":false,"name":"oo_37","parent":"root","transform":{"x":379.1,"y":408,"skX":-9.9846,"scX":0.584,"scY":0.584}},{"inheritScale":false,"name":"oo_38","parent":"root","transform":{"x":425.75,"y":411.3,"skX":-16.9788,"scX":0.384,"scY":0.384}},{"inheritScale":false,"name":"oo_39","parent":"root","transform":{"x":449.3,"y":353.5,"skX":-26.9791,"scX":0.4608,"scY":0.4608}},{"inheritScale":false,"name":"oo_40","parent":"root","transform":{"x":-393.25,"y":428,"skX":9.9999}},{"inheritScale":false,"name":"oo_41","parent":"root","transform":{"x":-297.75,"y":396.45,"skX":0.1819,"scX":0.9995,"scY":0.9995}},{"inheritScale":false,"name":"oo_42","parent":"root","transform":{"x":-354.45,"y":458.9,"skX":10.0009,"scX":0.64,"scY":0.64}},{"inheritScale":false,"name":"oo_43","parent":"root","transform":{"x":-333.55,"y":444.3,"skX":9.9991,"scX":0.512,"scY":0.512}},{"inheritScale":false,"name":"oo_44","parent":"root","transform":{"x":-319.1,"y":532.95,"skX":3.1879,"scX":0.5998,"scY":0.5998}},{"inheritScale":false,"name":"oo_45","parent":"root","transform":{"x":-357.55,"y":525.1,"skX":9.9998,"scX":0.384,"scY":0.384}},{"inheritScale":false,"name":"oo_46","parent":"root","transform":{"x":-386.3,"y":421.1,"skX":19.8138,"scX":0.4199,"scY":0.4199}},{"inheritScale":false,"name":"47","parent":"root"},{"inheritScale":false,"name":"48","parent":"root"},{"inheritScale":false,"name":"oo_49","parent":"root"}],"slot":[{"name":"dc_01","parent":"dc_01"},{"name":"dc_02","parent":"dc_02"},{"name":"dc_03","parent":"dc_03"},{"name":"oo_04","parent":"oo_04"},{"name":"oo_05","parent":"oo_05"},{"name":"dc_06","parent":"dc_06"},{"name":"oo_07","parent":"oo_07"},{"name":"oo_08","parent":"oo_08"},{"name":"oo_09","parent":"oo_09"},{"name":"dc_10","parent":"dc_10"},{"name":"dc_11","parent":"dc_11"},{"name":"oo_12","parent":"oo_12"},{"name":"oo_13","parent":"oo_13"},{"name":"oo_14","parent":"oo_14"},{"name":"oo_15","parent":"oo_15"},{"name":"oo_16","parent":"oo_16"},{"name":"oo_17","parent":"oo_17"},{"name":"oo_18","parent":"oo_18"},{"name":"oo_19","parent":"oo_19"},{"name":"oo_20","parent":"oo_20"},{"name":"oo_21","parent":"oo_21"},{"name":"oo_22","parent":"oo_22"},{"name":"oo_23","parent":"oo_23"},{"name":"oo_24","parent":"oo_24"},{"name":"oo_25","parent":"oo_25"},{"name":"oo_26","parent":"oo_26"},{"name":"oo_27","parent":"oo_27"},{"name":"oo_28","parent":"oo_28"},{"name":"oo_29","parent":"oo_29"},{"name":"oo_30","parent":"oo_30"},{"name":"oo_31","parent":"oo_31"},{"name":"oo_32","parent":"oo_32"},{"name":"oo_33","parent":"oo_33"},{"name":"oo_34","parent":"oo_34"},{"name":"oo_35","parent":"oo_35"},{"name":"oo_36","parent":"oo_36"},{"name":"oo_37","parent":"oo_37"},{"name":"oo_38","parent":"oo_38"},{"name":"oo_39","parent":"oo_39"},{"name":"oo_40","parent":"oo_40"},{"name":"oo_41","parent":"oo_41"},{"name":"oo_42","parent":"oo_42"},{"name":"oo_43","parent":"oo_43"},{"name":"oo_44","parent":"oo_44"},{"name":"oo_45","parent":"oo_45"},{"name":"oo_46","parent":"oo_46"},{"name":"47","parent":"47"},{"name":"48","parent":"48"},{"name":"oo_49","parent":"oo_49"}],"skin":[{"slot":[{"name":"oo_37","display":[{"name":"xhy_mianfei13"}]},{"name":"oo_17","display":[{"name":"xhy_mianfei13"}]},{"name":"oo_43","display":[{"name":"xhy_mianfei13"}]},{"name":"dc_06","display":[{"name":"xhy_mianfei15"}]},{"name":"oo_14","display":[{"name":"xhy_mianfei11"}]},{"name":"oo_23","display":[{"name":"xhy_mianfei13"}]},{"name":"oo_16","display":[{"name":"xhy_mianfei13"}]},{"name":"oo_26","display":[{"name":"xhy_mianfei13"}]},{"name":"47","display":[{"name":"xhy_mianfei03"}]},{"name":"oo_46","display":[{"name":"xhy_mianfei13"}]},{"name":"dc_02","display":[{"name":"xhy_mianfei15"}]},{"name":"oo_05","display":[{"name":"xhy_mianfei16"}]},{"name":"oo_08","display":[{"name":"xhy_mianfei16"}]},{"name":"oo_38","display":[{"name":"xhy_mianfei13"}]},{"name":"dc_03","display":[{"name":"xhy_mianfei15"}]},{"name":"dc_01","display":[{"name":"xhy_mianfei15"}]},{"name":"oo_41","display":[{"name":"xhy_mianfei11"}]},{"name":"oo_49","display":[{"name":"xhy_putong02"}]},{"name":"oo_12","display":[{"name":"xhy_mianfei13"}]},{"name":"dc_11","display":[{"name":"xhy_mianfei15"}]},{"name":"oo_04","display":[{"name":"xhy_mianfei16"}]},{"name":"oo_36","display":[{"name":"xhy_mianfei13"}]},{"name":"oo_28","display":[{"name":"xhy_mianfei11"}]},{"name":"oo_07","display":[{"name":"xhy_mianfei16"}]},{"name":"oo_18","display":[{"name":"xhy_mianfei13"}]},{"name":"oo_21","display":[{"name":"xhy_mianfei11"}]},{"name":"oo_30","display":[{"name":"xhy_mianfei13"}]},{"name":"oo_25","display":[{"name":"xhy_mianfei13"}]},{"name":"oo_34","display":[{"name":"xhy_mianfei11"}]},{"name":"oo_27","display":[{"name":"xhy_mianfei11"}]},{"name":"oo_40","display":[{"name":"xhy_mianfei13"}]},{"name":"oo_13","display":[{"name":"xhy_mianfei11"}]},{"name":"48","display":[{"name":"xhy_mianfei01"}]},{"name":"oo_22","display":[{"name":"xhy_mianfei13"}]},{"name":"oo_15","display":[{"name":"xhy_mianfei13"}]},{"name":"dc_10","display":[{"name":"xhy_mianfei15"}]},{"name":"oo_42","display":[{"name":"xhy_mianfei11"}]},{"name":"oo_39","display":[{"name":"xhy_mianfei13"}]},{"name":"oo_35","display":[{"name":"xhy_mianfei11"}]},{"name":"oo_44","display":[{"name":"xhy_mianfei13"}]},{"name":"oo_29","display":[{"name":"xhy_mianfei13"}]},{"name":"oo_31","display":[{"name":"xhy_mianfei13"}]},{"name":"oo_24","display":[{"name":"xhy_mianfei13"}]},{"name":"oo_09","display":[{"name":"xhy_mianfei16"}]},{"name":"oo_33","display":[{"name":"xhy_mianfei13"}]},{"name":"oo_45","display":[{"name":"xhy_mianfei13"}]},{"name":"oo_19","display":[{"name":"xhy_mianfei13"}]},{"name":"oo_20","display":[{"name":"xhy_mianfei11"}]},{"name":"oo_32","display":[{"name":"xhy_mianfei13"}]}]}],"animation":[{"duration":142,"playTimes":0,"name":"aixing","bone":[{"name":"oo_46","translateFrame":[{"duration":5,"tweenEasing":0},{"duration":2,"tweenEasing":0,"x":0.2,"y":-1.1},{"duration":15,"tweenEasing":0,"x":-2.5,"y":54.8},{"duration":17,"tweenEasing":0,"x":-4.7,"y":45.35},{"duration":15,"tweenEasing":0,"x":-6.45,"y":34.6},{"duration":15,"tweenEasing":0,"x":-1.5,"y":27.45},{"duration":2,"tweenEasing":0,"x":2.85,"y":21.05},{"duration":17,"tweenEasing":0,"x":3.5,"y":19.95},{"duration":17,"tweenEasing":0,"x":2.9,"y":14.8},{"duration":20,"tweenEasing":0,"x":0.1,"y":8.25},{"duration":15,"tweenEasing":0,"x":-0.65,"y":3.75},{"duration":2,"x":-0.05,"y":0.5}],"rotateFrame":[{"duration":5,"tweenEasing":0,"rotate":-160.18},{"duration":120,"tweenEasing":0,"rotate":-160},{"duration":15,"tweenEasing":0,"rotate":-160},{"duration":2,"rotate":-160.18}],"scaleFrame":[{"duration":5,"tweenEasing":0},{"duration":2,"tweenEasing":0,"x":0.99,"y":0.99},{"duration":98,"tweenEasing":0,"x":1.1,"y":1.1},{"duration":20,"tweenEasing":0,"x":1.1,"y":1.1},{"duration":15,"tweenEasing":0,"x":1.05,"y":1.05},{"duration":2,"x":1.01,"y":1.01}]},{"name":"oo_45","translateFrame":[{"duration":10,"tweenEasing":0},{"duration":17,"tweenEasing":0,"x":3,"y":-4.6},{"duration":15,"tweenEasing":0,"x":7.4,"y":-12.45},{"duration":17,"tweenEasing":0,"x":5.55,"y":-19.45},{"duration":10,"tweenEasing":0,"x":3.75,"y":-26.8},{"duration":2,"tweenEasing":0,"x":4.85,"y":-29},{"duration":5,"tweenEasing":0,"x":5.15,"y":-29.55},{"duration":17,"tweenEasing":0,"x":5.7,"y":-30.65},{"duration":20,"tweenEasing":0,"x":9.75,"y":-34.95},{"duration":22,"tweenEasing":0,"x":11.6,"y":-38.3},{"duration":2,"tweenEasing":0,"x":12.65,"y":-44.35},{"duration":2,"tweenEasing":0,"x":-1.45,"y":2.25},{"duration":3,"x":-0.7,"y":1.15}],"rotateFrame":[{"duration":142,"rotate":10}],"scaleFrame":[{"duration":93,"tweenEasing":0},{"duration":20,"tweenEasing":0},{"duration":22,"tweenEasing":0,"x":0.95,"y":0.95},{"duration":2,"tweenEasing":0,"x":0.9,"y":0.9},{"duration":5}]},{"name":"oo_44","translateFrame":[{"duration":7,"tweenEasing":0},{"duration":27,"tweenEasing":0,"x":5.75,"y":-9.1},{"duration":27,"tweenEasing":0,"x":3.6,"y":-31.05},{"duration":7,"tweenEasing":0,"x":12.85,"y":-43.1},{"duration":2,"tweenEasing":0,"x":12.65,"y":-45.6},{"duration":27,"tweenEasing":0,"x":12.6,"y":-46.4},{"duration":2,"tweenEasing":0,"x":11.75,"y":-55.45},{"duration":32,"tweenEasing":0,"x":319.1,"y":-532.95},{"duration":7,"tweenEasing":0,"x":-7.7,"y":12.1},{"duration":4,"x":-1.95,"y":3}],"rotateFrame":[{"duration":7,"tweenEasing":0,"rotate":3.19},{"duration":90,"tweenEasing":0,"rotate":3},{"duration":2,"tweenEasing":0,"rotate":3},{"duration":32,"tweenEasing":0},{"duration":7,"tweenEasing":0,"rotate":3},{"duration":4,"rotate":3.19}],"scaleFrame":[{"duration":61,"tweenEasing":0},{"duration":7,"tweenEasing":0},{"duration":2,"tweenEasing":0,"x":0.98,"y":0.98},{"duration":27,"tweenEasing":0,"x":0.97,"y":0.97},{"duration":2,"tweenEasing":0,"x":0.9,"y":0.9},{"duration":32,"tweenEasing":0,"x":1.67,"y":1.67},{"duration":11}]},{"name":"oo_43","translateFrame":[{"duration":27,"tweenEasing":0},{"duration":27,"tweenEasing":0,"x":-4.55,"y":-21.25},{"duration":15,"tweenEasing":0,"x":5,"y":-34.3},{"duration":2,"tweenEasing":0,"x":5.7,"y":-40.45},{"duration":20,"tweenEasing":0,"x":5.8,"y":-41.45},{"duration":2,"tweenEasing":0,"x":6.8,"y":-49.5},{"duration":30,"tweenEasing":0,"x":333.55,"y":-444.3},{"duration":17,"tweenEasing":0,"x":-13.95,"y":20.75},{"duration":2,"x":-1.75,"y":2.6}],"rotateFrame":[{"duration":91,"tweenEasing":0,"rotate":10},{"duration":2,"tweenEasing":0,"rotate":10},{"duration":30,"tweenEasing":0},{"duration":19,"rotate":10}],"scaleFrame":[{"duration":54,"tweenEasing":0},{"duration":15,"tweenEasing":0},{"duration":2,"tweenEasing":0,"x":0.96,"y":0.96},{"duration":20,"tweenEasing":0,"x":0.95,"y":0.95},{"duration":2,"tweenEasing":0,"x":0.9,"y":0.9},{"duration":30,"tweenEasing":0,"x":1.95,"y":1.95},{"duration":19}]},{"name":"oo_42","translateFrame":[{"duration":10,"tweenEasing":0},{"duration":27,"tweenEasing":0,"x":3.75,"y":-7.75},{"duration":32,"tweenEasing":0,"x":-1.25,"y":-23.2},{"duration":2,"tweenEasing":0,"x":3.7,"y":-33.65},{"duration":2,"tweenEasing":0,"x":4.1,"y":-34.45},{"duration":2,"tweenEasing":0,"x":4.45,"y":-35.2},{"duration":30,"tweenEasing":0,"x":354.45,"y":-458.9},{"duration":20,"tweenEasing":0,"x":-0.6,"y":38.65},{"duration":15,"tweenEasing":0,"x":-6.5,"y":13.6},{"duration":2,"x":-0.95,"y":2}],"rotateFrame":[{"duration":73,"tweenEasing":0,"rotate":-170},{"duration":2,"tweenEasing":0,"rotate":-170},{"duration":30,"tweenEasing":0},{"duration":37,"rotate":-170}],"scaleFrame":[{"duration":37,"tweenEasing":0},{"duration":32,"tweenEasing":0},{"duration":2,"tweenEasing":0,"x":0.91,"y":0.91},{"duration":2,"tweenEasing":0,"x":0.91,"y":0.91},{"duration":2,"tweenEasing":0,"x":0.9,"y":0.9},{"duration":30,"tweenEasing":0,"x":1.56,"y":1.56},{"duration":37}]},{"name":"oo_41","translateFrame":[{"duration":15,"tweenEasing":0},{"duration":37,"tweenEasing":0,"x":-4.25,"y":-13.25},{"duration":2,"tweenEasing":0,"x":4.65,"y":-32},{"duration":30,"tweenEasing":0,"x":297.75,"y":-396.45},{"duration":20,"tweenEasing":0,"x":-3.15,"y":83.45},{"duration":27,"tweenEasing":0,"x":-12.5,"y":44.25},{"duration":10,"tweenEasing":0,"x":3.5,"y":10.95},{"x":0.7,"y":2.25}],"rotateFrame":[{"duration":52,"tweenEasing":0,"rotate":180},{"duration":2,"tweenEasing":0,"rotate":180},{"duration":30,"tweenEasing":0},{"duration":58,"rotate":180}],"scaleFrame":[{"duration":15,"tweenEasing":0},{"duration":37,"tweenEasing":0},{"duration":2,"tweenEasing":0,"x":0.9,"y":0.9},{"duration":88}]},{"name":"oo_40","translateFrame":[{"duration":37,"tweenEasing":0},{"duration":2,"tweenEasing":0,"x":-1.9,"y":-20.6},{"duration":32,"tweenEasing":0,"x":393.25,"y":-428},{"duration":17,"tweenEasing":0,"x":-34.3,"y":92},{"duration":27,"tweenEasing":0,"x":-11.85,"y":56.85},{"duration":25,"tweenEasing":0,"x":-15.6,"y":20.15},{"duration":2,"x":-1.45,"y":1.85}],"rotateFrame":[{"duration":37,"tweenEasing":0,"rotate":10},{"duration":2,"tweenEasing":0,"rotate":10},{"duration":32,"tweenEasing":0},{"duration":71,"rotate":10}],"scaleFrame":[{"duration":37,"tweenEasing":0},{"duration":2,"tweenEasing":0,"x":0.9,"y":0.9},{"duration":103}]},{"name":"oo_39","translateFrame":[{"duration":17,"tweenEasing":0},{"duration":17,"tweenEasing":0,"y":-5.15},{"duration":20,"tweenEasing":0,"x":1.9,"y":-12.05},{"duration":22,"tweenEasing":0,"x":2.2,"y":-16.6},{"duration":2,"tweenEasing":0,"x":0.7,"y":-21.15},{"duration":15,"tweenEasing":0,"x":10.2,"y":34},{"duration":17,"tweenEasing":0,"x":11.2,"y":24.25},{"duration":15,"tweenEasing":0,"x":11.65,"y":13.3},{"duration":15,"tweenEasing":0,"x":5.85,"y":6.85},{"duration":2,"x":0.9,"y":1.3}],"rotateFrame":[{"duration":142,"rotate":-26.98}],"scaleFrame":[{"duration":34,"tweenEasing":0},{"duration":20,"tweenEasing":0},{"duration":22,"tweenEasing":0,"x":0.95,"y":0.95},{"duration":2,"tweenEasing":0,"x":0.9,"y":0.9},{"duration":64}]},{"name":"oo_38","translateFrame":[{"duration":5,"tweenEasing":0},{"duration":17,"tweenEasing":0,"x":-0.75,"y":-1.05},{"duration":20,"tweenEasing":0,"x":-5.3,"y":-4.75},{"duration":22,"tweenEasing":0,"x":-7.45,"y":-7.95},{"duration":2,"tweenEasing":0,"x":-9.3,"y":-13.75},{"duration":15,"tweenEasing":0,"x":10.4,"y":30.75},{"duration":17,"tweenEasing":0,"x":5.25,"y":24.6},{"duration":15,"tweenEasing":0,"x":-0.1,"y":17.2},{"duration":17,"tweenEasing":0,"x":0.9,"y":10.1},{"duration":10,"tweenEasing":0,"x":1.7,"y":2.6},{"duration":2,"x":0.45,"y":0.85}],"rotateFrame":[{"duration":42,"tweenEasing":0,"rotate":163.02},{"duration":22,"tweenEasing":0,"rotate":163.02},{"duration":2,"tweenEasing":0,"rotate":163.01},{"duration":76,"rotate":163.02}],"scaleFrame":[{"duration":22,"tweenEasing":0},{"duration":20,"tweenEasing":0},{"duration":22,"tweenEasing":0,"x":0.95,"y":0.95},{"duration":2,"tweenEasing":0,"x":0.9,"y":0.9},{"duration":76}]},{"name":"oo_37","translateFrame":[{"duration":27,"tweenEasing":0},{"duration":2,"tweenEasing":0,"x":-0.2,"y":-9.2},{"duration":32,"tweenEasing":0,"x":-379.1,"y":-408},{"duration":17,"tweenEasing":0,"x":27.3,"y":55.5},{"duration":27,"tweenEasing":0,"x":11.3,"y":36.2},{"duration":27,"tweenEasing":0,"x":10.75,"y":14.15},{"duration":7,"tweenEasing":0,"x":0.05,"y":3.25},{"duration":3,"x":0.15,"y":1.1}],"rotateFrame":[{"duration":27,"tweenEasing":0,"rotate":170.02},{"duration":2,"tweenEasing":0,"rotate":170.01},{"duration":32,"tweenEasing":0},{"duration":71,"tweenEasing":0,"rotate":170.02},{"duration":7,"tweenEasing":0,"rotate":170.02},{"duration":3,"rotate":170.01}],"scaleFrame":[{"duration":27,"tweenEasing":0},{"duration":2,"tweenEasing":0,"x":0.92,"y":0.92},{"duration":32,"tweenEasing":0,"x":1.71,"y":1.71},{"duration":71,"tweenEasing":0,"x":1.03,"y":1.03},{"duration":7,"tweenEasing":0,"x":1.03,"y":1.03},{"duration":3,"x":1.01,"y":1.01}]},{"name":"oo_36","translateFrame":[{"duration":20,"tweenEasing":0},{"duration":2,"tweenEasing":0,"x":-1.95,"y":-7.9},{"duration":30,"tweenEasing":0,"x":-390.05,"y":-322.25},{"duration":20,"tweenEasing":0,"x":27.15,"y":59.45},{"duration":27,"tweenEasing":0,"x":10.85,"y":40.5},{"duration":27,"tweenEasing":0,"x":12.65,"y":18.8},{"duration":15,"tweenEasing":0,"x":1.65,"y":7},{"x":0.35,"y":1.5}],"rotateFrame":[{"duration":20,"tweenEasing":0,"rotate":163.02},{"duration":2,"tweenEasing":0,"rotate":163.02},{"duration":30,"tweenEasing":0},{"duration":90,"rotate":163.02}],"scaleFrame":[{"duration":20,"tweenEasing":0},{"duration":2,"tweenEasing":0,"x":0.94,"y":0.94},{"duration":30,"tweenEasing":0,"x":2.05,"y":2.05},{"duration":74,"tweenEasing":0,"x":1.05,"y":1.05},{"duration":15,"tweenEasing":0,"x":1.05,"y":1.05},{"x":1.01,"y":1.01}]},{"name":"oo_35","translateFrame":[{"duration":2,"tweenEasing":0},{"duration":2,"tweenEasing":0,"x":-0.35,"y":-0.75},{"duration":30,"tweenEasing":0,"x":-414.95,"y":-341.05},{"duration":20,"tweenEasing":0,"x":13.6,"y":71.95},{"duration":27,"tweenEasing":0,"x":16.55,"y":46.3},{"duration":27,"tweenEasing":0,"x":3.65,"y":26.4},{"duration":32,"tweenEasing":0,"x":6.75,"y":10.4},{"duration":2,"x":0.75,"y":1}],"rotateFrame":[{"duration":2,"tweenEasing":0,"rotate":-16.98},{"duration":2,"tweenEasing":0,"rotate":-16.98},{"duration":30,"tweenEasing":0},{"duration":108,"rotate":-16.98}],"scaleFrame":[{"duration":2,"tweenEasing":0},{"duration":2,"tweenEasing":0,"x":0.99,"y":0.99},{"duration":30,"tweenEasing":0,"x":1.72,"y":1.72},{"duration":74,"tweenEasing":0,"x":1.1,"y":1.1},{"duration":32,"tweenEasing":0,"x":1.1,"y":1.1},{"duration":2,"x":1.01,"y":1.01}]},{"name":"oo_34","translateFrame":[{"duration":12,"tweenEasing":0},{"duration":20,"tweenEasing":0,"x":372.75,"y":402.05},{"duration":27,"tweenEasing":0,"x":377.2,"y":361.85},{"duration":27,"tweenEasing":0,"x":357.2,"y":330.9},{"duration":37,"tweenEasing":0,"x":362,"y":306},{"duration":2,"tweenEasing":0,"x":350.85,"y":288.45},{"duration":17}],"rotateFrame":[{"duration":12,"tweenEasing":0},{"duration":111,"tweenEasing":0,"rotate":-6.98},{"duration":2,"tweenEasing":0,"rotate":-6.98},{"duration":17}],"scaleFrame":[{"duration":86,"tweenEasing":0},{"duration":37,"tweenEasing":0},{"duration":2,"tweenEasing":0,"x":0.9,"y":0.9},{"duration":17}]},{"name":"oo_33","translateFrame":[{"duration":17,"tweenEasing":0},{"duration":27,"tweenEasing":0,"x":-26.45,"y":-32.3},{"duration":27,"tweenEasing":0,"x":-27.3,"y":-69.1},{"duration":37,"tweenEasing":0,"x":-45.35,"y":-87.2},{"duration":2,"tweenEasing":0,"x":-45.8,"y":-107.9},{"duration":32,"x":-503.3,"y":-426.5}],"rotateFrame":[{"duration":108,"tweenEasing":0,"rotate":163.02},{"duration":2,"tweenEasing":0,"rotate":163.02},{"duration":32}],"scaleFrame":[{"duration":71,"tweenEasing":0},{"duration":37,"tweenEasing":0},{"duration":2,"tweenEasing":0,"x":0.9,"y":0.9},{"duration":32}]},{"name":"oo_32","translateFrame":[{"duration":7,"tweenEasing":0},{"duration":22,"tweenEasing":0,"x":-0.45,"y":-1.6},{"duration":2,"tweenEasing":0,"x":-0.45,"y":-6.5},{"duration":15,"tweenEasing":0,"x":6.55,"y":49.05},{"duration":17,"tweenEasing":0,"x":2.75,"y":40.05},{"duration":15,"tweenEasing":0,"x":-0.8,"y":29.8},{"duration":15,"tweenEasing":0,"x":2.8,"y":21.9},{"duration":2,"tweenEasing":0,"x":5.95,"y":14.85},{"duration":17,"tweenEasing":0,"x":6.45,"y":13.65},{"duration":17,"tweenEasing":0,"x":4.95,"y":8.7},{"duration":10,"tweenEasing":0,"x":1.05,"y":2.7},{"duration":3,"x":0.25,"y":0.55}],"rotateFrame":[{"duration":142,"rotate":-170}],"scaleFrame":[{"duration":7,"tweenEasing":0},{"duration":22,"tweenEasing":0,"x":0.98,"y":0.98},{"duration":2,"tweenEasing":0,"x":0.93,"y":0.93},{"duration":98,"tweenEasing":0,"x":1.03,"y":1.03},{"duration":10,"tweenEasing":0,"x":1.03,"y":1.03},{"duration":3,"x":1.01,"y":1.01}]},{"name":"oo_31","translateFrame":[{"duration":17,"tweenEasing":0},{"duration":2,"tweenEasing":0,"y":-4.8},{"duration":15,"tweenEasing":0,"x":-5.85,"y":43.5},{"duration":17,"tweenEasing":0,"x":-2.65,"y":36},{"duration":15,"tweenEasing":0,"x":0.3,"y":27.45},{"duration":17,"tweenEasing":0,"x":-2.7,"y":20.9},{"duration":10,"tweenEasing":0,"x":-5.75,"y":14},{"duration":2,"tweenEasing":0,"x":-5.05,"y":11.65},{"duration":5,"tweenEasing":0,"x":-4.85,"y":11.05},{"duration":17,"tweenEasing":0,"x":-4.5,"y":9.9},{"duration":20,"tweenEasing":0,"x":-1.25,"y":4.9},{"duration":2,"tweenEasing":0,"y":1.3},{"duration":3,"y":0.6}],"scaleFrame":[{"duration":17,"tweenEasing":0},{"duration":2,"tweenEasing":0,"x":0.96,"y":0.96},{"duration":98,"tweenEasing":0,"x":1.06,"y":1.06},{"duration":20,"tweenEasing":0,"x":1.06,"y":1.06},{"duration":5,"x":1.01,"y":1.01}]},{"name":"oo_30","translateFrame":[{"duration":15,"tweenEasing":0},{"duration":17,"tweenEasing":0,"x":236.55,"y":536.75},{"duration":27,"tweenEasing":0,"x":246.15,"y":513.65},{"duration":27,"tweenEasing":0,"x":240.15,"y":492.35},{"duration":7,"tweenEasing":0,"x":247.25,"y":478.85},{"duration":2,"tweenEasing":0,"x":246.6,"y":476.45},{"duration":27,"tweenEasing":0,"x":246.4,"y":475.65},{"duration":2,"tweenEasing":0,"x":243.95,"y":466.85},{"duration":18}],"rotateFrame":[{"duration":15,"tweenEasing":0},{"duration":107,"tweenEasing":0,"rotate":-7},{"duration":2,"tweenEasing":0,"rotate":-7},{"duration":18}],"scaleFrame":[{"duration":15,"tweenEasing":0},{"duration":71,"tweenEasing":0,"x":0.6,"y":0.6},{"duration":7,"tweenEasing":0,"x":0.6,"y":0.6},{"duration":2,"tweenEasing":0,"x":0.59,"y":0.59},{"duration":27,"tweenEasing":0,"x":0.58,"y":0.58},{"duration":2,"tweenEasing":0,"x":0.54,"y":0.54},{"duration":18}]},{"name":"oo_29","translateFrame":[{"duration":5,"tweenEasing":0},{"duration":20,"tweenEasing":0,"x":202.25,"y":461.65},{"duration":27,"tweenEasing":0,"x":212.4,"y":438.75},{"duration":27,"tweenEasing":0,"x":204.3,"y":418.55},{"duration":15,"tweenEasing":0,"x":211.35,"y":404.05},{"duration":2,"tweenEasing":0,"x":211,"y":397.95},{"duration":20,"tweenEasing":0,"x":210.9,"y":396.95},{"duration":2,"tweenEasing":0,"x":210.5,"y":388.8},{"duration":24}],"scaleFrame":[{"duration":5,"tweenEasing":0},{"duration":74,"tweenEasing":0,"x":0.51,"y":0.51},{"duration":15,"tweenEasing":0,"x":0.51,"y":0.51},{"duration":2,"tweenEasing":0,"x":0.49,"y":0.49},{"duration":20,"tweenEasing":0,"x":0.49,"y":0.49},{"duration":2,"tweenEasing":0,"x":0.46,"y":0.46},{"duration":24}]},{"name":"oo_28","translateFrame":[{"duration":7,"tweenEasing":0},{"duration":27,"tweenEasing":0,"x":-3.85,"y":-8.85},{"duration":27,"tweenEasing":0,"x":2.55,"y":-31.6},{"duration":32,"tweenEasing":0,"x":-5.05,"y":-46},{"duration":2,"tweenEasing":0,"x":-1.95,"y":-57.1},{"duration":2,"tweenEasing":0,"x":-1.7,"y":-57.95},{"duration":2,"tweenEasing":0,"x":-1.5,"y":-58.8},{"duration":30,"tweenEasing":0,"x":-194.15,"y":-480.1},{"duration":10,"tweenEasing":0,"x":6.35,"y":14.8},{"duration":3,"x":1.25,"y":3}],"rotateFrame":[{"duration":97,"tweenEasing":0,"rotate":180},{"duration":2,"tweenEasing":0,"rotate":180},{"duration":30,"tweenEasing":0},{"duration":13,"rotate":180}],"scaleFrame":[{"duration":61,"tweenEasing":0},{"duration":32,"tweenEasing":0},{"duration":2,"tweenEasing":0,"x":0.91,"y":0.91},{"duration":2,"tweenEasing":0,"x":0.91,"y":0.91},{"duration":2,"tweenEasing":0,"x":0.9,"y":0.9},{"duration":30,"tweenEasing":0,"x":1.56,"y":1.56},{"duration":13}]},{"name":"oo_27","translateFrame":[{"duration":12,"tweenEasing":0},{"duration":27,"tweenEasing":0,"x":4.55,"y":-16.15},{"duration":37,"tweenEasing":0,"x":-7.3,"y":-38.65},{"duration":2,"tweenEasing":0,"x":-1.8,"y":-58.65},{"duration":30,"tweenEasing":0,"x":-240.2,"y":-411.75},{"duration":20,"tweenEasing":0,"x":10.55,"y":56.35},{"duration":12,"tweenEasing":0,"x":-5.45,"y":19.35},{"duration":2,"x":-0.9,"y":3.2}],"rotateFrame":[{"duration":12,"tweenEasing":0,"rotate":170.18},{"duration":64,"tweenEasing":0,"rotate":170},{"duration":2,"tweenEasing":0,"rotate":170},{"duration":30,"tweenEasing":0},{"duration":20,"tweenEasing":0,"rotate":170},{"duration":12,"tweenEasing":0,"rotate":170},{"duration":2,"rotate":170.18}],"scaleFrame":[{"duration":39,"tweenEasing":0},{"duration":37,"tweenEasing":0},{"duration":2,"tweenEasing":0,"x":0.9,"y":0.9},{"duration":64}]},{"name":"oo_26","translateFrame":[{"duration":25,"tweenEasing":0},{"duration":37,"tweenEasing":0,"x":10.75,"y":-20.45},{"duration":2,"tweenEasing":0,"x":5.25,"y":-40.45},{"duration":32,"tweenEasing":0,"x":-140.05,"y":-453.55},{"duration":17,"tweenEasing":0,"x":-7.1,"y":76.05},{"duration":27,"tweenEasing":0,"x":8.9,"y":37.55},{"duration":2,"x":-1.1,"y":2.05}],"scaleFrame":[{"duration":25,"tweenEasing":0},{"duration":37,"tweenEasing":0},{"duration":2,"tweenEasing":0,"x":0.9,"y":0.9},{"duration":78}]},{"name":"oo_25","translateFrame":[{"duration":5,"tweenEasing":0},{"duration":2,"tweenEasing":0,"y":-1.1},{"duration":15,"tweenEasing":0,"x":-7,"y":54.45},{"duration":17,"tweenEasing":0,"x":-3.2,"y":45.45},{"duration":15,"tweenEasing":0,"x":0.35,"y":35.2},{"duration":15,"tweenEasing":0,"x":-3.25,"y":27.3},{"duration":2,"tweenEasing":0,"x":-6.4,"y":20.25},{"duration":17,"tweenEasing":0,"x":-6.9,"y":19.05},{"duration":17,"tweenEasing":0,"x":-5.4,"y":14.1},{"duration":20,"tweenEasing":0,"x":-1.5,"y":8.1},{"duration":15,"tweenEasing":0,"y":3.8},{"duration":2,"x":0.05,"y":0.5}],"rotateFrame":[{"duration":5,"tweenEasing":0,"rotate":-9.82},{"duration":120,"tweenEasing":0,"rotate":-10},{"duration":15,"tweenEasing":0,"rotate":-10},{"duration":2,"rotate":-9.82}],"scaleFrame":[{"duration":5,"tweenEasing":0},{"duration":2,"tweenEasing":0,"x":0.99,"y":0.99},{"duration":98,"tweenEasing":0,"x":1.1,"y":1.1},{"duration":20,"tweenEasing":0,"x":1.1,"y":1.1},{"duration":15,"tweenEasing":0,"x":1.05,"y":1.05},{"duration":2,"x":1.01,"y":1.01}]},{"name":"oo_24","translateFrame":[{"duration":10,"tweenEasing":0},{"duration":17,"tweenEasing":0,"x":-2.15,"y":-5},{"duration":15,"tweenEasing":0,"x":-5.1,"y":-13.55},{"duration":17,"tweenEasing":0,"x":-2.1,"y":-20.1},{"duration":10,"tweenEasing":0,"x":0.95,"y":-27},{"duration":2,"tweenEasing":0,"x":0.25,"y":-29.35},{"duration":5,"tweenEasing":0,"x":0.05,"y":-29.95},{"duration":17,"tweenEasing":0,"x":-0.3,"y":-31.1},{"duration":20,"tweenEasing":0,"x":-3.55,"y":-36.1},{"duration":22,"tweenEasing":0,"x":-4.8,"y":-39.7},{"duration":2,"tweenEasing":0,"x":-4.8,"y":-45.8},{"duration":2,"tweenEasing":0,"x":1.05,"y":2.5},{"duration":3,"x":0.5,"y":1.25}],"rotateFrame":[{"duration":142,"rotate":180}],"scaleFrame":[{"duration":93,"tweenEasing":0},{"duration":20,"tweenEasing":0},{"duration":22,"tweenEasing":0,"x":0.95,"y":0.95},{"duration":2,"tweenEasing":0,"x":0.9,"y":0.9},{"duration":5}]},{"name":"oo_23","translateFrame":[{"duration":7,"tweenEasing":0},{"duration":27,"tweenEasing":0,"x":-4.15,"y":-9.85},{"duration":27,"tweenEasing":0,"x":1.85,"y":-31.15},{"duration":7,"tweenEasing":0,"x":-5.25,"y":-44.65},{"duration":2,"tweenEasing":0,"x":-4.6,"y":-47.05},{"duration":27,"tweenEasing":0,"x":-4.4,"y":-47.85},{"duration":2,"tweenEasing":0,"x":-1.95,"y":-56.65},{"duration":32,"tweenEasing":0,"x":625.1,"y":-447.5},{"duration":7,"tweenEasing":0,"x":5.45,"y":13.25},{"duration":4,"x":1.4,"y":3.3}],"rotateFrame":[{"duration":7,"tweenEasing":0,"rotate":-173.19},{"duration":90,"tweenEasing":0,"rotate":-173},{"duration":2,"tweenEasing":0,"rotate":-173},{"duration":32,"tweenEasing":0},{"duration":7,"tweenEasing":0,"rotate":-173},{"duration":4,"rotate":-173.19}],"scaleFrame":[{"duration":61,"tweenEasing":0},{"duration":7,"tweenEasing":0},{"duration":2,"tweenEasing":0,"x":0.98,"y":0.98},{"duration":27,"tweenEasing":0,"x":0.97,"y":0.97},{"duration":2,"tweenEasing":0,"x":0.9,"y":0.9},{"duration":32,"tweenEasing":0,"x":1.67,"y":1.67},{"duration":11}]},{"name":"oo_22","translateFrame":[{"duration":27,"tweenEasing":0},{"duration":27,"tweenEasing":0,"x":8.1,"y":-20.2},{"duration":15,"tweenEasing":0,"x":1.05,"y":-34.7},{"duration":2,"tweenEasing":0,"x":1.4,"y":-40.8},{"duration":20,"tweenEasing":0,"x":1.5,"y":-41.8},{"duration":2,"tweenEasing":0,"x":1.9,"y":-49.95},{"duration":30,"tweenEasing":0,"x":595.5,"y":-362.75},{"duration":17,"tweenEasing":0,"x":10.15,"y":22.9},{"duration":2,"x":1.25,"y":2.85}],"rotateFrame":[{"duration":91,"tweenEasing":0,"rotate":180},{"duration":2,"tweenEasing":0,"rotate":180},{"duration":30,"tweenEasing":0},{"duration":19,"rotate":180}],"scaleFrame":[{"duration":54,"tweenEasing":0},{"duration":15,"tweenEasing":0},{"duration":2,"tweenEasing":0,"x":0.96,"y":0.96},{"duration":20,"tweenEasing":0,"x":0.95,"y":0.95},{"duration":2,"tweenEasing":0,"x":0.9,"y":0.9},{"duration":30,"tweenEasing":0,"x":1.95,"y":1.95},{"duration":19}]},{"name":"oo_21","translateFrame":[{"duration":10,"tweenEasing":0},{"duration":27,"tweenEasing":0,"x":-2.35,"y":-8.25},{"duration":32,"tweenEasing":0,"x":5.25,"y":-22.65},{"duration":2,"tweenEasing":0,"x":2.15,"y":-33.75},{"duration":2,"tweenEasing":0,"x":1.9,"y":-34.6},{"duration":2,"tweenEasing":0,"x":1.7,"y":-35.45},{"duration":30,"tweenEasing":0,"x":577.45,"y":-380.75},{"duration":20,"tweenEasing":0,"x":-6.15,"y":38.15},{"duration":15,"tweenEasing":0,"x":4.05,"y":14.5},{"duration":2,"x":0.55,"y":2.1}],"scaleFrame":[{"duration":37,"tweenEasing":0},{"duration":32,"tweenEasing":0},{"duration":2,"tweenEasing":0,"x":0.91,"y":0.91},{"duration":2,"tweenEasing":0,"x":0.91,"y":0.91},{"duration":2,"tweenEasing":0,"x":0.9,"y":0.9},{"duration":30,"tweenEasing":0,"x":1.56,"y":1.56},{"duration":37}]},{"name":"oo_20","translateFrame":[{"duration":15,"tweenEasing":0},{"duration":37,"tweenEasing":0,"x":6.5,"y":-12.25},{"duration":2,"tweenEasing":0,"x":1,"y":-32.25},{"duration":30,"tweenEasing":0,"x":622.5,"y":-309.35},{"duration":20,"tweenEasing":0,"x":-11.35,"y":82.75},{"duration":27,"tweenEasing":0,"x":4.65,"y":45.75},{"duration":10,"tweenEasing":0,"x":-5.35,"y":10.25},{"x":-1.1,"y":2.05}],"rotateFrame":[{"duration":15,"tweenEasing":0,"rotate":9.82},{"duration":37,"tweenEasing":0,"rotate":10},{"duration":2,"tweenEasing":0,"rotate":10},{"duration":30,"tweenEasing":0},{"duration":47,"tweenEasing":0,"rotate":10},{"duration":10,"tweenEasing":0,"rotate":10},{"rotate":9.82}],"scaleFrame":[{"duration":15,"tweenEasing":0},{"duration":37,"tweenEasing":0},{"duration":2,"tweenEasing":0,"x":0.9,"y":0.9},{"duration":88}]},{"name":"oo_19","translateFrame":[{"duration":37,"tweenEasing":0},{"duration":2,"tweenEasing":0,"x":5.5,"y":-20},{"duration":32,"tweenEasing":0,"x":533.9,"y":-357.1},{"duration":17,"tweenEasing":0,"x":17.85,"y":96.5},{"duration":27,"tweenEasing":0,"x":1.85,"y":58},{"duration":25,"tweenEasing":0,"x":11.85,"y":22.5},{"duration":2,"x":1.1,"y":2.05}],"rotateFrame":[{"duration":37,"tweenEasing":0,"rotate":180},{"duration":2,"tweenEasing":0,"rotate":180},{"duration":32,"tweenEasing":0},{"duration":71,"rotate":180}],"scaleFrame":[{"duration":37,"tweenEasing":0},{"duration":2,"tweenEasing":0,"x":0.9,"y":0.9},{"duration":103}]},{"name":"oo_18","translateFrame":[{"duration":17,"tweenEasing":0},{"duration":17,"tweenEasing":0,"x":-0.15,"y":-5.1},{"duration":20,"tweenEasing":0,"x":-2.35,"y":-11.85},{"duration":22,"tweenEasing":0,"x":-2.7,"y":-16.5},{"duration":2,"tweenEasing":0,"x":-1.45,"y":-21.2},{"duration":15,"tweenEasing":0,"x":-9.05,"y":34.3},{"duration":17,"tweenEasing":0,"x":-10.45,"y":24.6},{"duration":15,"tweenEasing":0,"x":-11.15,"y":13.75},{"duration":15,"tweenEasing":0,"x":-5.7,"y":7.15},{"duration":2,"x":-0.75,"y":1.1}],"rotateFrame":[{"duration":142,"rotate":-155}],"scaleFrame":[{"duration":34,"tweenEasing":0},{"duration":20,"tweenEasing":0},{"duration":22,"tweenEasing":0,"x":0.95,"y":0.95},{"duration":2,"tweenEasing":0,"x":0.9,"y":0.9},{"duration":64}]},{"name":"oo_17","translateFrame":[{"duration":5,"tweenEasing":0},{"duration":17,"tweenEasing":0,"x":0.65,"y":-1},{"duration":20,"tweenEasing":0,"x":5.1,"y":-4.95},{"duration":22,"tweenEasing":0,"x":7.3,"y":-8.1},{"duration":2,"tweenEasing":0,"x":8.85,"y":-14},{"duration":15,"tweenEasing":0,"x":-9.3,"y":31.2},{"duration":17,"tweenEasing":0,"x":-4.25,"y":24.75},{"duration":15,"tweenEasing":0,"x":0.8,"y":17.2},{"duration":17,"tweenEasing":0,"x":-0.4,"y":10.1},{"duration":10,"tweenEasing":0,"x":-1.55,"y":2.7},{"duration":2,"x":-0.35,"y":0.6}],"rotateFrame":[{"duration":142,"rotate":15}],"scaleFrame":[{"duration":22,"tweenEasing":0},{"duration":20,"tweenEasing":0},{"duration":22,"tweenEasing":0,"x":0.95,"y":0.95},{"duration":2,"tweenEasing":0,"x":0.9,"y":0.9},{"duration":76}]},{"name":"oo_16","translateFrame":[{"duration":27,"tweenEasing":0},{"duration":2,"tweenEasing":0,"x":-0.05,"y":-9.2},{"duration":32,"tweenEasing":0,"x":712.2,"y":-362.55},{"duration":17,"tweenEasing":0,"x":-25.35,"y":56.45},{"duration":27,"tweenEasing":0,"x":-10.1,"y":36.65},{"duration":27,"tweenEasing":0,"x":-10.35,"y":14.55},{"duration":7,"tweenEasing":0,"y":3.35},{"duration":3,"y":0.85}],"rotateFrame":[{"duration":27,"tweenEasing":0,"rotate":8},{"duration":2,"tweenEasing":0,"rotate":8},{"duration":32,"tweenEasing":0},{"duration":81,"rotate":8}],"scaleFrame":[{"duration":27,"tweenEasing":0},{"duration":2,"tweenEasing":0,"x":0.92,"y":0.92},{"duration":32,"tweenEasing":0,"x":1.71,"y":1.71},{"duration":71,"tweenEasing":0,"x":1.03,"y":1.03},{"duration":7,"tweenEasing":0,"x":1.03,"y":1.03},{"duration":3,"x":1.01,"y":1.01}]},{"name":"oo_15","translateFrame":[{"duration":20,"tweenEasing":0},{"duration":2,"tweenEasing":0,"x":1.7,"y":-8},{"duration":30,"tweenEasing":0,"x":726.1,"y":-277.35},{"duration":20,"tweenEasing":0,"x":-25.1,"y":60.25},{"duration":27,"tweenEasing":0,"x":-9.4,"y":40.75},{"duration":27,"tweenEasing":0,"x":-11.95,"y":19.2},{"duration":15,"tweenEasing":0,"x":-1.35,"y":6.95},{"x":-0.2,"y":0.95}],"rotateFrame":[{"duration":20,"tweenEasing":0,"rotate":15},{"duration":2,"tweenEasing":0,"rotate":15},{"duration":30,"tweenEasing":0},{"duration":90,"rotate":15}],"scaleFrame":[{"duration":20,"tweenEasing":0},{"duration":2,"tweenEasing":0,"x":0.94,"y":0.94},{"duration":30,"tweenEasing":0,"x":2.05,"y":2.05},{"duration":74,"tweenEasing":0,"x":1.05,"y":1.05},{"duration":15,"tweenEasing":0,"x":1.05,"y":1.05},{"x":1.01,"y":1.01}]},{"name":"oo_14","translateFrame":[{"duration":2,"tweenEasing":0},{"duration":2,"tweenEasing":0,"x":0.4,"y":-0.75},{"duration":30,"tweenEasing":0,"x":750.45,"y":-296.9},{"duration":20,"tweenEasing":0,"x":-11.05,"y":72.35},{"duration":27,"tweenEasing":0,"x":-14.75,"y":46.9},{"duration":27,"tweenEasing":0,"x":-2.7,"y":26.5},{"duration":32,"tweenEasing":0,"x":-6.25,"y":10.7},{"duration":2,"x":-0.45,"y":0.75}],"rotateFrame":[{"duration":2,"tweenEasing":0,"rotate":-165},{"duration":2,"tweenEasing":0,"rotate":-165},{"duration":30,"tweenEasing":0},{"duration":108,"rotate":-165}],"scaleFrame":[{"duration":2,"tweenEasing":0},{"duration":2,"tweenEasing":0,"x":0.99,"y":0.99},{"duration":30,"tweenEasing":0,"x":1.72,"y":1.72},{"duration":74,"tweenEasing":0,"x":1.1,"y":1.1},{"duration":32,"tweenEasing":0,"x":1.1,"y":1.1},{"duration":2,"x":1.01,"y":1.01}]},{"name":"oo_13","translateFrame":[{"duration":12,"tweenEasing":0},{"duration":20,"tweenEasing":0,"x":-706.05,"y":356.35},{"duration":27,"tweenEasing":0,"x":-711.9,"y":316.45},{"duration":27,"tweenEasing":0,"x":-693.05,"y":284.8},{"duration":37,"tweenEasing":0,"x":-698.7,"y":260},{"duration":2,"tweenEasing":0,"x":-688.15,"y":242.1},{"duration":17}],"rotateFrame":[{"duration":12,"tweenEasing":0},{"duration":111,"tweenEasing":0,"rotate":-175},{"duration":2,"tweenEasing":0,"rotate":-175},{"duration":17}],"scaleFrame":[{"duration":86,"tweenEasing":0},{"duration":37,"tweenEasing":0},{"duration":2,"tweenEasing":0,"x":0.9,"y":0.9},{"duration":17}]},{"name":"oo_12","translateFrame":[{"duration":17,"tweenEasing":0},{"duration":27,"tweenEasing":0,"x":25.4,"y":-33},{"duration":27,"tweenEasing":0,"x":24.95,"y":-69.85},{"duration":37,"tweenEasing":0,"x":42.15,"y":-88.55},{"duration":2,"tweenEasing":0,"x":42.05,"y":-109.25},{"duration":32,"x":835.7,"y":-385.25}],"rotateFrame":[{"duration":108,"tweenEasing":0,"rotate":15},{"duration":2,"tweenEasing":0,"rotate":15},{"duration":32}],"scaleFrame":[{"duration":71,"tweenEasing":0},{"duration":37,"tweenEasing":0},{"duration":2,"tweenEasing":0,"x":0.9,"y":0.9},{"duration":32}]},{"name":"dc_11","translateFrame":[{"duration":20,"tweenEasing":0},{"duration":72,"tweenEasing":0,"x":0.1},{"duration":50,"tweenEasing":0,"x":0.1},{"duration":0}]},{"name":"dc_10","translateFrame":[{"duration":5,"tweenEasing":0},{"duration":74,"tweenEasing":0,"x":0.1},{"duration":62,"tweenEasing":0,"x":0.1},{}]},{"name":"oo_09","translateFrame":[{"duration":20,"tweenEasing":0},{"duration":74,"tweenEasing":0,"y":-0.05},{"duration":47,"tweenEasing":0,"y":-0.05},{}]},{"name":"dc_03","translateFrame":[{"duration":15,"tweenEasing":0},{"duration":72,"tweenEasing":0,"x":0.05,"y":-0.05},{"duration":55,"tweenEasing":0,"x":0.05,"y":-0.05},{"duration":0}]},{"name":"dc_02","translateFrame":[{"duration":30,"tweenEasing":0},{"duration":74,"tweenEasing":0,"y":0.05},{"duration":37,"tweenEasing":0,"y":0.05},{}]}],"slot":[{"name":"oo_46","colorFrame":[{"duration":5,"tweenEasing":0,"value":{"aM":4}},{"duration":2,"tweenEasing":0,"value":{"aM":0}},{"duration":15,"tweenEasing":0,"value":{"aM":0}},{"duration":17,"tweenEasing":0,"value":{"aM":19}},{"duration":66,"tweenEasing":0,"value":{"aM":39}},{"duration":20,"tweenEasing":0,"value":{"aM":39}},{"duration":15,"tweenEasing":0,"value":{"aM":20}},{"duration":2,"value":{"aM":6}}]},{"name":"oo_45","colorFrame":[{"duration":10,"tweenEasing":0,"value":{"aM":6}},{"duration":17,"tweenEasing":0,"value":{"aM":19}},{"duration":66,"tweenEasing":0,"value":{"aM":39}},{"duration":20,"tweenEasing":0,"value":{"aM":39}},{"duration":22,"tweenEasing":0,"value":{"aM":20}},{"duration":2,"tweenEasing":0,"value":{"aM":0}},{"duration":2,"tweenEasing":0,"value":{"aM":0}},{"duration":3,"value":{"aM":3}}]},{"name":"oo_44","displayFrame":[{"duration":99},{"duration":32,"value":-1},{"duration":11}],"colorFrame":[{"duration":7,"tweenEasing":0,"value":{"aM":26}},{"duration":54,"tweenEasing":0,"value":{"aM":39}},{"duration":7,"tweenEasing":0,"value":{"aM":39}},{"duration":2,"tweenEasing":0,"value":{"aM":31}},{"duration":27,"tweenEasing":0,"value":{"aM":28}},{"duration":2,"value":{"aM":0}},{"duration":32,"tweenEasing":0},{"duration":7,"tweenEasing":0,"value":{"aM":9}},{"duration":4,"value":{"aM":22}}]},{"name":"oo_43","displayFrame":[{"duration":93},{"duration":30,"value":-1},{"duration":19}],"colorFrame":[{"duration":54,"tweenEasing":0,"value":{"aM":39}},{"duration":15,"tweenEasing":0,"value":{"aM":39}},{"duration":2,"tweenEasing":0,"value":{"aM":23}},{"duration":20,"tweenEasing":0,"value":{"aM":20}},{"duration":2,"value":{"aM":0}},{"duration":30,"tweenEasing":0},{"duration":17,"tweenEasing":0,"value":{"aM":9}},{"duration":2,"value":{"aM":35}}]},{"name":"oo_42","displayFrame":[{"duration":75},{"duration":30,"value":-1},{"duration":37}],"colorFrame":[{"duration":37,"tweenEasing":0,"value":{"aM":39}},{"duration":32,"tweenEasing":0,"value":{"aM":39}},{"duration":2,"tweenEasing":0,"value":{"aM":4}},{"duration":2,"tweenEasing":0,"value":{"aM":2}},{"duration":2,"value":{"aM":0}},{"duration":30,"tweenEasing":0},{"duration":20,"tweenEasing":0,"value":{"aM":9}},{"duration":17,"value":{"aM":39}}]},{"name":"oo_41","displayFrame":[{"duration":54},{"duration":30,"value":-1},{"duration":58}],"colorFrame":[{"duration":15,"tweenEasing":0,"value":{"aM":39}},{"duration":37,"tweenEasing":0,"value":{"aM":39}},{"duration":2,"value":{"aM":0}},{"duration":30,"tweenEasing":0},{"duration":20,"tweenEasing":0,"value":{"aM":9}},{"duration":38,"value":{"aM":39}}]},{"name":"oo_40","displayFrame":[{"duration":39},{"duration":32,"value":-1},{"duration":71}],"colorFrame":[{"duration":37,"tweenEasing":0,"value":{"aM":39}},{"duration":2,"value":{"aM":0}},{"duration":32,"tweenEasing":0},{"duration":17,"tweenEasing":0,"value":{"aM":9}},{"duration":54,"value":{"aM":39}}]},{"name":"oo_39","colorFrame":[{"duration":34,"tweenEasing":0,"value":{"aM":39}},{"duration":20,"tweenEasing":0,"value":{"aM":39}},{"duration":22,"tweenEasing":0,"value":{"aM":20}},{"duration":2,"tweenEasing":0,"value":{"aM":0}},{"duration":15,"tweenEasing":0,"value":{"aM":0}},{"duration":17,"tweenEasing":0,"value":{"aM":19}},{"duration":32,"value":{"aM":39}}]},{"name":"oo_38","colorFrame":[{"duration":22,"tweenEasing":0,"value":{"aM":39}},{"duration":20,"tweenEasing":0,"value":{"aM":39}},{"duration":22,"tweenEasing":0,"value":{"aM":20}},{"duration":2,"tweenEasing":0,"value":{"aM":0}},{"duration":15,"tweenEasing":0,"value":{"aM":0}},{"duration":17,"tweenEasing":0,"value":{"aM":19}},{"duration":44,"value":{"aM":39}}]},{"name":"oo_37","displayFrame":[{"duration":29},{"duration":32,"value":-1},{"duration":81}],"colorFrame":[{"duration":27,"tweenEasing":0,"value":{"aM":28}},{"duration":2,"value":{"aM":0}},{"duration":32,"tweenEasing":0},{"duration":17,"tweenEasing":0,"value":{"aM":9}},{"duration":54,"tweenEasing":0,"value":{"aM":39}},{"duration":7,"tweenEasing":0,"value":{"aM":39}},{"duration":3,"value":{"aM":31}}]},{"name":"oo_36","displayFrame":[{"duration":22},{"duration":30,"value":-1},{"duration":90}],"colorFrame":[{"duration":20,"tweenEasing":0,"value":{"aM":20}},{"duration":2,"value":{"aM":0}},{"duration":30,"tweenEasing":0},{"duration":20,"tweenEasing":0,"value":{"aM":9}},{"duration":54,"tweenEasing":0,"value":{"aM":39}},{"duration":15,"tweenEasing":0,"value":{"aM":39}},{"value":{"aM":23}}]},{"name":"oo_35","displayFrame":[{"duration":4},{"duration":30,"value":-1},{"duration":108}],"colorFrame":[{"duration":2,"tweenEasing":0,"value":{"aM":2}},{"duration":2,"value":{"aM":0}},{"duration":30,"tweenEasing":0},{"duration":20,"tweenEasing":0,"value":{"aM":9}},{"duration":54,"tweenEasing":0,"value":{"aM":39}},{"duration":32,"tweenEasing":0,"value":{"aM":39}},{"duration":2,"value":{"aM":4}}]},{"name":"oo_34","displayFrame":[{"duration":12,"value":-1},{"duration":113},{"duration":17,"value":-1}],"colorFrame":[{"duration":12,"tweenEasing":0},{"duration":20,"tweenEasing":0,"value":{"aM":9}},{"duration":54,"tweenEasing":0,"value":{"aM":39}},{"duration":37,"tweenEasing":0,"value":{"aM":39}},{"duration":2,"value":{"aM":0}},{"duration":17}]},{"name":"oo_33","displayFrame":[{"duration":110},{"duration":32,"value":-1}],"colorFrame":[{"duration":17,"tweenEasing":0,"value":{"aM":9}},{"duration":54,"tweenEasing":0,"value":{"aM":39}},{"duration":37,"tweenEasing":0,"value":{"aM":39}},{"duration":2,"value":{"aM":0}},{"duration":32}]},{"name":"oo_32","colorFrame":[{"duration":7,"tweenEasing":0,"value":{"aM":27}},{"duration":22,"tweenEasing":0,"value":{"aM":20}},{"duration":2,"tweenEasing":0,"value":{"aM":0}},{"duration":15,"tweenEasing":0,"value":{"aM":0}},{"duration":17,"tweenEasing":0,"value":{"aM":19}},{"duration":66,"tweenEasing":0,"value":{"aM":39}},{"duration":10,"tweenEasing":0,"value":{"aM":39}},{"duration":3,"value":{"aM":28}}]},{"name":"oo_31","colorFrame":[{"duration":17,"tweenEasing":0,"value":{"aM":16}},{"duration":2,"tweenEasing":0,"value":{"aM":0}},{"duration":15,"tweenEasing":0,"value":{"aM":0}},{"duration":17,"tweenEasing":0,"value":{"aM":19}},{"duration":66,"tweenEasing":0,"value":{"aM":39}},{"duration":20,"tweenEasing":0,"value":{"aM":39}},{"duration":2,"tweenEasing":0,"value":{"aM":20}},{"duration":3,"value":{"aM":18}}]},{"name":"oo_30","displayFrame":[{"duration":15,"value":-1},{"duration":109},{"duration":18,"value":-1}],"colorFrame":[{"duration":15,"tweenEasing":0},{"duration":17,"tweenEasing":0,"value":{"aM":9}},{"duration":54,"tweenEasing":0,"value":{"aM":39}},{"duration":7,"tweenEasing":0,"value":{"aM":39}},{"duration":2,"tweenEasing":0,"value":{"aM":31}},{"duration":27,"tweenEasing":0,"value":{"aM":28}},{"duration":2,"value":{"aM":0}},{"duration":18}]},{"name":"oo_29","displayFrame":[{"duration":5,"value":-1},{"duration":113},{"duration":24,"value":-1}],"colorFrame":[{"duration":5,"tweenEasing":0},{"duration":20,"tweenEasing":0,"value":{"aM":9}},{"duration":54,"tweenEasing":0,"value":{"aM":39}},{"duration":15,"tweenEasing":0,"value":{"aM":39}},{"duration":2,"tweenEasing":0,"value":{"aM":23}},{"duration":20,"tweenEasing":0,"value":{"aM":20}},{"duration":2,"value":{"aM":0}},{"duration":24}]},{"name":"oo_28","displayFrame":[{"duration":99},{"duration":30,"value":-1},{"duration":13}],"colorFrame":[{"duration":7,"tweenEasing":0,"value":{"aM":28}},{"duration":54,"tweenEasing":0,"value":{"aM":39}},{"duration":32,"tweenEasing":0,"value":{"aM":39}},{"duration":2,"tweenEasing":0,"value":{"aM":4}},{"duration":2,"tweenEasing":0,"value":{"aM":2}},{"duration":2,"value":{"aM":0}},{"duration":30,"tweenEasing":0},{"duration":10,"tweenEasing":0,"value":{"aM":9}},{"duration":3,"value":{"aM":24}}]},{"name":"oo_27","displayFrame":[{"duration":78},{"duration":30,"value":-1},{"duration":34}],"colorFrame":[{"duration":39,"tweenEasing":0,"value":{"aM":39}},{"duration":37,"tweenEasing":0,"value":{"aM":39}},{"duration":2,"value":{"aM":0}},{"duration":30,"tweenEasing":0},{"duration":20,"tweenEasing":0,"value":{"aM":9}},{"duration":14,"value":{"aM":39}}]},{"name":"oo_26","displayFrame":[{"duration":64},{"duration":32,"value":-1},{"duration":46}],"colorFrame":[{"duration":25,"tweenEasing":0,"value":{"aM":39}},{"duration":37,"tweenEasing":0,"value":{"aM":39}},{"duration":2,"value":{"aM":0}},{"duration":32,"tweenEasing":0},{"duration":17,"tweenEasing":0,"value":{"aM":9}},{"duration":29,"value":{"aM":39}}]},{"name":"oo_25","colorFrame":[{"duration":5,"tweenEasing":0,"value":{"aM":4}},{"duration":2,"tweenEasing":0,"value":{"aM":0}},{"duration":15,"tweenEasing":0,"value":{"aM":0}},{"duration":17,"tweenEasing":0,"value":{"aM":19}},{"duration":66,"tweenEasing":0,"value":{"aM":39}},{"duration":20,"tweenEasing":0,"value":{"aM":39}},{"duration":15,"tweenEasing":0,"value":{"aM":20}},{"duration":2,"value":{"aM":6}}]},{"name":"oo_24","colorFrame":[{"duration":10,"tweenEasing":0,"value":{"aM":6}},{"duration":17,"tweenEasing":0,"value":{"aM":19}},{"duration":66,"tweenEasing":0,"value":{"aM":39}},{"duration":20,"tweenEasing":0,"value":{"aM":39}},{"duration":22,"tweenEasing":0,"value":{"aM":20}},{"duration":2,"tweenEasing":0,"value":{"aM":0}},{"duration":2,"tweenEasing":0,"value":{"aM":0}},{"duration":3,"value":{"aM":3}}]},{"name":"oo_23","displayFrame":[{"duration":99},{"duration":32,"value":-1},{"duration":11}],"colorFrame":[{"duration":7,"tweenEasing":0,"value":{"aM":26}},{"duration":54,"tweenEasing":0,"value":{"aM":39}},{"duration":7,"tweenEasing":0,"value":{"aM":39}},{"duration":2,"tweenEasing":0,"value":{"aM":31}},{"duration":27,"tweenEasing":0,"value":{"aM":28}},{"duration":2,"value":{"aM":0}},{"duration":32,"tweenEasing":0},{"duration":7,"tweenEasing":0,"value":{"aM":9}},{"duration":4,"value":{"aM":22}}]},{"name":"oo_22","displayFrame":[{"duration":93},{"duration":30,"value":-1},{"duration":19}],"colorFrame":[{"duration":54,"tweenEasing":0,"value":{"aM":39}},{"duration":15,"tweenEasing":0,"value":{"aM":39}},{"duration":2,"tweenEasing":0,"value":{"aM":23}},{"duration":20,"tweenEasing":0,"value":{"aM":20}},{"duration":2,"value":{"aM":0}},{"duration":30,"tweenEasing":0},{"duration":17,"tweenEasing":0,"value":{"aM":9}},{"duration":2,"value":{"aM":35}}]},{"name":"oo_21","displayFrame":[{"duration":75},{"duration":30,"value":-1},{"duration":37}],"colorFrame":[{"duration":37,"tweenEasing":0,"value":{"aM":39}},{"duration":32,"tweenEasing":0,"value":{"aM":39}},{"duration":2,"tweenEasing":0,"value":{"aM":4}},{"duration":2,"tweenEasing":0,"value":{"aM":2}},{"duration":2,"value":{"aM":0}},{"duration":30,"tweenEasing":0},{"duration":20,"tweenEasing":0,"value":{"aM":9}},{"duration":17,"value":{"aM":39}}]},{"name":"oo_20","displayFrame":[{"duration":54},{"duration":30,"value":-1},{"duration":58}],"colorFrame":[{"duration":15,"tweenEasing":0,"value":{"aM":39}},{"duration":37,"tweenEasing":0,"value":{"aM":39}},{"duration":2,"value":{"aM":0}},{"duration":30,"tweenEasing":0},{"duration":20,"tweenEasing":0,"value":{"aM":9}},{"duration":38,"value":{"aM":39}}]},{"name":"oo_19","displayFrame":[{"duration":39},{"duration":32,"value":-1},{"duration":71}],"colorFrame":[{"duration":37,"tweenEasing":0,"value":{"aM":39}},{"duration":2,"value":{"aM":0}},{"duration":32,"tweenEasing":0},{"duration":17,"tweenEasing":0,"value":{"aM":9}},{"duration":54,"value":{"aM":39}}]},{"name":"oo_18","colorFrame":[{"duration":34,"tweenEasing":0,"value":{"aM":39}},{"duration":20,"tweenEasing":0,"value":{"aM":39}},{"duration":22,"tweenEasing":0,"value":{"aM":20}},{"duration":2,"tweenEasing":0,"value":{"aM":0}},{"duration":15,"tweenEasing":0,"value":{"aM":0}},{"duration":17,"tweenEasing":0,"value":{"aM":19}},{"duration":32,"value":{"aM":39}}]},{"name":"oo_17","colorFrame":[{"duration":22,"tweenEasing":0,"value":{"aM":39}},{"duration":20,"tweenEasing":0,"value":{"aM":39}},{"duration":22,"tweenEasing":0,"value":{"aM":20}},{"duration":2,"tweenEasing":0,"value":{"aM":0}},{"duration":15,"tweenEasing":0,"value":{"aM":0}},{"duration":17,"tweenEasing":0,"value":{"aM":19}},{"duration":44,"value":{"aM":39}}]},{"name":"oo_16","displayFrame":[{"duration":29},{"duration":32,"value":-1},{"duration":81}],"colorFrame":[{"duration":27,"tweenEasing":0,"value":{"aM":28}},{"duration":2,"value":{"aM":0}},{"duration":32,"tweenEasing":0},{"duration":17,"tweenEasing":0,"value":{"aM":9}},{"duration":54,"tweenEasing":0,"value":{"aM":39}},{"duration":7,"tweenEasing":0,"value":{"aM":39}},{"duration":3,"value":{"aM":31}}]},{"name":"oo_15","displayFrame":[{"duration":22},{"duration":30,"value":-1},{"duration":90}],"colorFrame":[{"duration":20,"tweenEasing":0,"value":{"aM":20}},{"duration":2,"value":{"aM":0}},{"duration":30,"tweenEasing":0},{"duration":20,"tweenEasing":0,"value":{"aM":9}},{"duration":54,"tweenEasing":0,"value":{"aM":39}},{"duration":15,"tweenEasing":0,"value":{"aM":39}},{"value":{"aM":23}}]},{"name":"oo_14","displayFrame":[{"duration":4},{"duration":30,"value":-1},{"duration":108}],"colorFrame":[{"duration":2,"tweenEasing":0,"value":{"aM":2}},{"duration":2,"value":{"aM":0}},{"duration":30,"tweenEasing":0},{"duration":20,"tweenEasing":0,"value":{"aM":9}},{"duration":54,"tweenEasing":0,"value":{"aM":39}},{"duration":32,"tweenEasing":0,"value":{"aM":39}},{"duration":2,"value":{"aM":4}}]},{"name":"oo_13","displayFrame":[{"duration":12,"value":-1},{"duration":113},{"duration":17,"value":-1}],"colorFrame":[{"duration":12,"tweenEasing":0},{"duration":20,"tweenEasing":0,"value":{"aM":9}},{"duration":54,"tweenEasing":0,"value":{"aM":39}},{"duration":37,"tweenEasing":0,"value":{"aM":39}},{"duration":2,"value":{"aM":0}},{"duration":17}]},{"name":"oo_12","displayFrame":[{"duration":110},{"duration":32,"value":-1}],"colorFrame":[{"duration":17,"tweenEasing":0,"value":{"aM":9}},{"duration":54,"tweenEasing":0,"value":{"aM":39}},{"duration":37,"tweenEasing":0,"value":{"aM":39}},{"duration":2,"value":{"aM":0}},{"duration":32}]},{"name":"dc_11","colorFrame":[{"duration":20,"tweenEasing":0,"value":{"aM":56}},{"duration":70,"tweenEasing":0,"value":{"aM":80}},{"duration":2,"tweenEasing":0,"value":{"aM":0}},{"duration":50,"tweenEasing":0,"value":{"aM":0}},{"duration":0,"value":{"aM":54}}]},{"name":"dc_10","colorFrame":[{"duration":5,"tweenEasing":0,"value":{"aM":55}},{"duration":72,"tweenEasing":0,"value":{"aM":60}},{"duration":2,"tweenEasing":0,"value":{"aM":0}},{"duration":62,"tweenEasing":0,"value":{"aM":0}},{"value":{"aM":53}}]},{"name":"oo_09","colorFrame":[{"duration":20,"tweenEasing":0,"value":{"aM":28}},{"duration":72,"tweenEasing":0,"value":{"aM":39}},{"duration":2,"tweenEasing":0,"value":{"aM":0}},{"duration":47,"tweenEasing":0,"value":{"aM":0}},{"value":{"aM":26}}]},{"name":"oo_08","colorFrame":[{"duration":55,"tweenEasing":0,"value":{"aM":28}},{"duration":2,"tweenEasing":0,"value":{"aM":0}},{"duration":70,"tweenEasing":0,"value":{"aM":0}},{"duration":15,"tweenEasing":0,"value":{"aM":39}},{"duration":0,"value":{"aM":31}}]},{"name":"oo_07","colorFrame":[{"duration":12,"tweenEasing":0,"value":{"aM":6}},{"duration":2,"tweenEasing":0,"value":{"aM":0}},{"duration":70,"tweenEasing":0,"value":{"aM":0}},{"duration":57,"tweenEasing":0,"value":{"aM":39}},{"value":{"aM":7}}]},{"name":"dc_06","colorFrame":[{"duration":70,"tweenEasing":0,"value":{"aM":0}},{"duration":72,"tweenEasing":0,"value":{"aM":80}},{"duration":0,"value":{"aM":0}}]},{"name":"oo_05","colorFrame":[{"duration":55,"tweenEasing":0,"value":{"aM":28}},{"duration":2,"tweenEasing":0,"value":{"aM":0}},{"duration":70,"tweenEasing":0,"value":{"aM":0}},{"duration":15,"tweenEasing":0,"value":{"aM":39}},{"duration":0,"value":{"aM":31}}]},{"name":"oo_04","colorFrame":[{"duration":12,"tweenEasing":0,"value":{"aM":6}},{"duration":2,"tweenEasing":0,"value":{"aM":0}},{"duration":70,"tweenEasing":0,"value":{"aM":0}},{"duration":57,"tweenEasing":0,"value":{"aM":39}},{"value":{"aM":7}}]},{"name":"dc_03","colorFrame":[{"duration":15,"tweenEasing":0,"value":{"aM":12}},{"duration":2,"tweenEasing":0,"value":{"aM":0}},{"duration":70,"tweenEasing":0,"value":{"aM":0}},{"duration":55,"tweenEasing":0,"value":{"aM":60}},{"duration":0,"value":{"aM":13}}]},{"name":"dc_02","colorFrame":[{"duration":30,"tweenEasing":0,"value":{"aM":33}},{"duration":2,"tweenEasing":0,"value":{"aM":0}},{"duration":72,"tweenEasing":0,"value":{"aM":0}},{"duration":37,"tweenEasing":0,"value":{"aM":80}},{"value":{"aM":36}}]},{"name":"dc_01","colorFrame":[{"duration":70,"tweenEasing":0},{"duration":72,"tweenEasing":0,"value":{"aM":0}},{"duration":0}]},{"name":"47","displayFrame":[{"duration":142,"value":-1}]},{"name":"48","displayFrame":[{"duration":142,"value":-1}]},{"name":"oo_49","displayFrame":[{"duration":142,"value":-1}]}]},{"duration":121,"playTimes":0,"name":"dianliang","bone":[{"name":"47","translateFrame":[{"duration":27,"tweenEasing":0,"x":410.35,"y":-351.6},{"duration":2,"tweenEasing":0,"x":410.35,"y":-351.6},{"duration":92}]}],"slot":[{"name":"47","displayFrame":[{"duration":29},{"duration":92,"value":-1}],"colorFrame":[{"duration":5,"tweenEasing":0,"value":{"aM":0}},{"duration":10,"tweenEasing":0},{"duration":12,"tweenEasing":0},{"duration":2,"value":{"aM":0}},{"duration":92}]},{"name":"dc_01","displayFrame":[{"duration":121,"value":-1}]},{"name":"dc_02","displayFrame":[{"duration":121,"value":-1}]},{"name":"dc_03","displayFrame":[{"duration":121,"value":-1}]},{"name":"oo_04","displayFrame":[{"duration":121,"value":-1}]},{"name":"oo_05","displayFrame":[{"duration":121,"value":-1}]},{"name":"dc_06","displayFrame":[{"duration":121,"value":-1}]},{"name":"oo_07","displayFrame":[{"duration":121,"value":-1}]},{"name":"oo_08","displayFrame":[{"duration":121,"value":-1}]},{"name":"oo_09","displayFrame":[{"duration":121,"value":-1}]},{"name":"dc_10","displayFrame":[{"duration":121,"value":-1}]},{"name":"dc_11","displayFrame":[{"duration":121,"value":-1}]},{"name":"oo_12","displayFrame":[{"duration":121,"value":-1}]},{"name":"oo_13","displayFrame":[{"duration":121,"value":-1}]},{"name":"oo_14","displayFrame":[{"duration":121,"value":-1}]},{"name":"oo_15","displayFrame":[{"duration":121,"value":-1}]},{"name":"oo_16","displayFrame":[{"duration":121,"value":-1}]},{"name":"oo_17","displayFrame":[{"duration":121,"value":-1}]},{"name":"oo_18","displayFrame":[{"duration":121,"value":-1}]},{"name":"oo_19","displayFrame":[{"duration":121,"value":-1}]},{"name":"oo_20","displayFrame":[{"duration":121,"value":-1}]},{"name":"oo_21","displayFrame":[{"duration":121,"value":-1}]},{"name":"oo_22","displayFrame":[{"duration":121,"value":-1}]},{"name":"oo_23","displayFrame":[{"duration":121,"value":-1}]},{"name":"oo_24","displayFrame":[{"duration":121,"value":-1}]},{"name":"oo_25","displayFrame":[{"duration":121,"value":-1}]},{"name":"oo_26","displayFrame":[{"duration":121,"value":-1}]},{"name":"oo_27","displayFrame":[{"duration":121,"value":-1}]},{"name":"oo_28","displayFrame":[{"duration":121,"value":-1}]},{"name":"oo_29","displayFrame":[{"duration":121,"value":-1}]},{"name":"oo_30","displayFrame":[{"duration":121,"value":-1}]},{"name":"oo_31","displayFrame":[{"duration":121,"value":-1}]},{"name":"oo_32","displayFrame":[{"duration":121,"value":-1}]},{"name":"oo_33","displayFrame":[{"duration":121,"value":-1}]},{"name":"oo_34","displayFrame":[{"duration":121,"value":-1}]},{"name":"oo_35","displayFrame":[{"duration":121,"value":-1}]},{"name":"oo_36","displayFrame":[{"duration":121,"value":-1}]},{"name":"oo_37","displayFrame":[{"duration":121,"value":-1}]},{"name":"oo_38","displayFrame":[{"duration":121,"value":-1}]},{"name":"oo_39","displayFrame":[{"duration":121,"value":-1}]},{"name":"oo_40","displayFrame":[{"duration":121,"value":-1}]},{"name":"oo_41","displayFrame":[{"duration":121,"value":-1}]},{"name":"oo_42","displayFrame":[{"duration":121,"value":-1}]},{"name":"oo_43","displayFrame":[{"duration":121,"value":-1}]},{"name":"oo_44","displayFrame":[{"duration":121,"value":-1}]},{"name":"oo_45","displayFrame":[{"duration":121,"value":-1}]},{"name":"oo_46","displayFrame":[{"duration":121,"value":-1}]},{"name":"48","displayFrame":[{"duration":121,"value":-1}]},{"name":"oo_49","displayFrame":[{"duration":121,"value":-1}]}]},{"duration":54,"playTimes":0,"name":"hongxing","bone":[{"name":"48","translateFrame":[{"duration":42,"tweenEasing":0,"x":-451,"y":-344},{"duration":2,"tweenEasing":0,"x":-451,"y":-344},{"duration":10}]}],"slot":[{"name":"48","displayFrame":[{"duration":44},{"duration":10,"value":-1}],"colorFrame":[{"duration":10,"tweenEasing":0,"value":{"aM":0}},{"duration":20,"tweenEasing":0},{"duration":12,"tweenEasing":0},{"duration":2,"value":{"aM":0}},{"duration":10}]},{"name":"dc_01","displayFrame":[{"duration":54,"value":-1}]},{"name":"dc_02","displayFrame":[{"duration":54,"value":-1}]},{"name":"dc_03","displayFrame":[{"duration":54,"value":-1}]},{"name":"oo_04","displayFrame":[{"duration":54,"value":-1}]},{"name":"oo_05","displayFrame":[{"duration":54,"value":-1}]},{"name":"dc_06","displayFrame":[{"duration":54,"value":-1}]},{"name":"oo_07","displayFrame":[{"duration":54,"value":-1}]},{"name":"oo_08","displayFrame":[{"duration":54,"value":-1}]},{"name":"oo_09","displayFrame":[{"duration":54,"value":-1}]},{"name":"dc_10","displayFrame":[{"duration":54,"value":-1}]},{"name":"dc_11","displayFrame":[{"duration":54,"value":-1}]},{"name":"oo_12","displayFrame":[{"duration":54,"value":-1}]},{"name":"oo_13","displayFrame":[{"duration":54,"value":-1}]},{"name":"oo_14","displayFrame":[{"duration":54,"value":-1}]},{"name":"oo_15","displayFrame":[{"duration":54,"value":-1}]},{"name":"oo_16","displayFrame":[{"duration":54,"value":-1}]},{"name":"oo_17","displayFrame":[{"duration":54,"value":-1}]},{"name":"oo_18","displayFrame":[{"duration":54,"value":-1}]},{"name":"oo_19","displayFrame":[{"duration":54,"value":-1}]},{"name":"oo_20","displayFrame":[{"duration":54,"value":-1}]},{"name":"oo_21","displayFrame":[{"duration":54,"value":-1}]},{"name":"oo_22","displayFrame":[{"duration":54,"value":-1}]},{"name":"oo_23","displayFrame":[{"duration":54,"value":-1}]},{"name":"oo_24","displayFrame":[{"duration":54,"value":-1}]},{"name":"oo_25","displayFrame":[{"duration":54,"value":-1}]},{"name":"oo_26","displayFrame":[{"duration":54,"value":-1}]},{"name":"oo_27","displayFrame":[{"duration":54,"value":-1}]},{"name":"oo_28","displayFrame":[{"duration":54,"value":-1}]},{"name":"oo_29","displayFrame":[{"duration":54,"value":-1}]},{"name":"oo_30","displayFrame":[{"duration":54,"value":-1}]},{"name":"oo_31","displayFrame":[{"duration":54,"value":-1}]},{"name":"oo_32","displayFrame":[{"duration":54,"value":-1}]},{"name":"oo_33","displayFrame":[{"duration":54,"value":-1}]},{"name":"oo_34","displayFrame":[{"duration":54,"value":-1}]},{"name":"oo_35","displayFrame":[{"duration":54,"value":-1}]},{"name":"oo_36","displayFrame":[{"duration":54,"value":-1}]},{"name":"oo_37","displayFrame":[{"duration":54,"value":-1}]},{"name":"oo_38","displayFrame":[{"duration":54,"value":-1}]},{"name":"oo_39","displayFrame":[{"duration":54,"value":-1}]},{"name":"oo_40","displayFrame":[{"duration":54,"value":-1}]},{"name":"oo_41","displayFrame":[{"duration":54,"value":-1}]},{"name":"oo_42","displayFrame":[{"duration":54,"value":-1}]},{"name":"oo_43","displayFrame":[{"duration":54,"value":-1}]},{"name":"oo_44","displayFrame":[{"duration":54,"value":-1}]},{"name":"oo_45","displayFrame":[{"duration":54,"value":-1}]},{"name":"oo_46","displayFrame":[{"duration":54,"value":-1}]},{"name":"47","displayFrame":[{"duration":54,"value":-1}]},{"name":"oo_49","displayFrame":[{"duration":54,"value":-1}]}]},{"duration":168,"playTimes":0,"name":"diannao","bone":[{"name":"oo_49","translateFrame":[{"duration":7,"tweenEasing":0},{"duration":144,"tweenEasing":0,"x":650,"y":140.55},{"duration":2,"tweenEasing":0,"x":650,"y":140.55},{"duration":15}],"scaleFrame":[{"duration":7,"tweenEasing":0},{"duration":144,"tweenEasing":0,"x":2,"y":2},{"duration":2,"tweenEasing":0,"x":2,"y":2},{"duration":15}]}],"slot":[{"name":"oo_49","displayFrame":[{"duration":7,"value":-1},{"duration":146},{"duration":15,"value":-1}],"colorFrame":[{"duration":7,"tweenEasing":0},{"duration":137,"value":{"aM":69}},{"duration":7,"tweenEasing":0,"value":{"aM":69}},{"duration":2,"value":{"aM":0}},{"duration":15}]},{"name":"dc_01","displayFrame":[{"duration":168,"value":-1}]},{"name":"dc_02","displayFrame":[{"duration":168,"value":-1}]},{"name":"dc_03","displayFrame":[{"duration":168,"value":-1}]},{"name":"oo_04","displayFrame":[{"duration":168,"value":-1}]},{"name":"oo_05","displayFrame":[{"duration":168,"value":-1}]},{"name":"dc_06","displayFrame":[{"duration":168,"value":-1}]},{"name":"oo_07","displayFrame":[{"duration":168,"value":-1}]},{"name":"oo_08","displayFrame":[{"duration":168,"value":-1}]},{"name":"oo_09","displayFrame":[{"duration":168,"value":-1}]},{"name":"dc_10","displayFrame":[{"duration":168,"value":-1}]},{"name":"dc_11","displayFrame":[{"duration":168,"value":-1}]},{"name":"oo_12","displayFrame":[{"duration":168,"value":-1}]},{"name":"oo_13","displayFrame":[{"duration":168,"value":-1}]},{"name":"oo_14","displayFrame":[{"duration":168,"value":-1}]},{"name":"oo_15","displayFrame":[{"duration":168,"value":-1}]},{"name":"oo_16","displayFrame":[{"duration":168,"value":-1}]},{"name":"oo_17","displayFrame":[{"duration":168,"value":-1}]},{"name":"oo_18","displayFrame":[{"duration":168,"value":-1}]},{"name":"oo_19","displayFrame":[{"duration":168,"value":-1}]},{"name":"oo_20","displayFrame":[{"duration":168,"value":-1}]},{"name":"oo_21","displayFrame":[{"duration":168,"value":-1}]},{"name":"oo_22","displayFrame":[{"duration":168,"value":-1}]},{"name":"oo_23","displayFrame":[{"duration":168,"value":-1}]},{"name":"oo_24","displayFrame":[{"duration":168,"value":-1}]},{"name":"oo_25","displayFrame":[{"duration":168,"value":-1}]},{"name":"oo_26","displayFrame":[{"duration":168,"value":-1}]},{"name":"oo_27","displayFrame":[{"duration":168,"value":-1}]},{"name":"oo_28","displayFrame":[{"duration":168,"value":-1}]},{"name":"oo_29","displayFrame":[{"duration":168,"value":-1}]},{"name":"oo_30","displayFrame":[{"duration":168,"value":-1}]},{"name":"oo_31","displayFrame":[{"duration":168,"value":-1}]},{"name":"oo_32","displayFrame":[{"duration":168,"value":-1}]},{"name":"oo_33","displayFrame":[{"duration":168,"value":-1}]},{"name":"oo_34","displayFrame":[{"duration":168,"value":-1}]},{"name":"oo_35","displayFrame":[{"duration":168,"value":-1}]},{"name":"oo_36","displayFrame":[{"duration":168,"value":-1}]},{"name":"oo_37","displayFrame":[{"duration":168,"value":-1}]},{"name":"oo_38","displayFrame":[{"duration":168,"value":-1}]},{"name":"oo_39","displayFrame":[{"duration":168,"value":-1}]},{"name":"oo_40","displayFrame":[{"duration":168,"value":-1}]},{"name":"oo_41","displayFrame":[{"duration":168,"value":-1}]},{"name":"oo_42","displayFrame":[{"duration":168,"value":-1}]},{"name":"oo_43","displayFrame":[{"duration":168,"value":-1}]},{"name":"oo_44","displayFrame":[{"duration":168,"value":-1}]},{"name":"oo_45","displayFrame":[{"duration":168,"value":-1}]},{"name":"oo_46","displayFrame":[{"duration":168,"value":-1}]},{"name":"47","displayFrame":[{"duration":168,"value":-1}]},{"name":"48","displayFrame":[{"duration":168,"value":-1}]}]}],"defaultActions":[{"gotoAndPlay":"aixing"}]}]}